binoauth/__init__.py
binoauth/admin/__init__.py
binoauth/admin/api_client.py
binoauth/admin/api_response.py
binoauth/admin/configuration.py
binoauth/admin/exceptions.py
binoauth/admin/rest.py
binoauth/admin/api/__init__.py
binoauth/admin/api/admin_api.py
binoauth/admin/api/admin_authentication_api.py
binoauth/admin/api/health_api.py
binoauth/admin/models/__init__.py
binoauth/admin/models/api_key_create.py
binoauth/admin/models/api_key_create_response.py
binoauth/admin/models/api_key_list_response.py
binoauth/admin/models/api_key_response.py
binoauth/admin/models/api_key_status.py
binoauth/admin/models/api_key_update.py
binoauth/admin/models/client_auth_methods.py
binoauth/admin/models/client_create.py
binoauth/admin/models/client_response.py
binoauth/admin/models/client_update.py
binoauth/admin/models/domain.py
binoauth/admin/models/external_account.py
binoauth/admin/models/http_validation_error.py
binoauth/admin/models/in_line_client_config.py
binoauth/admin/models/management_login_request.py
binoauth/admin/models/management_refresh_token_request.py
binoauth/admin/models/management_signup_request.py
binoauth/admin/models/management_signup_response.py
binoauth/admin/models/management_social_login_request.py
binoauth/admin/models/management_token_response.py
binoauth/admin/models/management_user_response.py
binoauth/admin/models/pagination_result_client_response.py
binoauth/admin/models/pagination_result_tenant_response.py
binoauth/admin/models/pagination_result_user_with_external_accounts.py
binoauth/admin/models/provider_settings_create.py
binoauth/admin/models/provider_settings_response.py
binoauth/admin/models/provider_settings_update.py
binoauth/admin/models/provider_type.py
binoauth/admin/models/tenant_create_request.py
binoauth/admin/models/tenant_response.py
binoauth/admin/models/tenant_update_request.py
binoauth/admin/models/user_create.py
binoauth/admin/models/user_response.py
binoauth/admin/models/user_status.py
binoauth-0.0.5.dist-info/METADATA
binoauth-0.0.5.dist-info/WHEEL
binoauth-0.0.5.dist-info/top_level.txt
binoauth-0.0.5.dist-info/RECORD
