Metadata-Version: 2.4
Name: binoauth
Version: 0.0.5
Summary: Multi-tenant authentication and authorization Python SDK supporting OAuth2, OpenID Connect, API keys, and multiple authentication methods
Author-email: Binoauth <support@binoauth.com>
License: MIT
Project-URL: Homepage, https://binoauth.com
Project-URL: Documentation, https://docs.binoauth.com
Project-URL: Repository, https://github.com/binoauth/binoauth-python-sdk
Project-URL: Bug Tracker, https://github.com/binoauth/binoauth-python-sdk/issues
Keywords: authentication,authorization,oauth2,openid-connect,api,sdk,multi-tenant
Classifier: Development Status :: 4 - Beta
Classifier: Intended Audience :: Developers
Classifier: License :: OSI Approved :: MIT License
Classifier: Operating System :: OS Independent
Classifier: Programming Language :: Python :: 3
Classifier: Programming Language :: Python :: 3.9
Classifier: Programming Language :: Python :: 3.10
Classifier: Programming Language :: Python :: 3.11
Classifier: Programming Language :: Python :: 3.12
Classifier: Topic :: Software Development :: Libraries :: Python Modules
Classifier: Topic :: System :: Systems Administration :: Authentication/Directory
Requires-Python: >=3.9
Requires-Dist: urllib3>=1.25.3
Requires-Dist: python-dateutil>=2.8.0
Requires-Dist: pydantic>=1.10.0
Requires-Dist: typing-extensions>=4.0.0
Provides-Extra: dev
Requires-Dist: pytest>=7.0.0; extra == "dev"
Requires-Dist: pytest-cov>=4.0.0; extra == "dev"
Requires-Dist: black>=23.0.0; extra == "dev"
Requires-Dist: isort>=5.12.0; extra == "dev"
Requires-Dist: mypy>=1.0.0; extra == "dev"
Requires-Dist: pre-commit>=3.0.0; extra == "dev"
Requires-Dist: bump-my-version>=1.2.1; extra == "dev"
Requires-Dist: build>=0.10.0; extra == "dev"
Requires-Dist: twine>=4.0.0; extra == "dev"
